loralib/__init__.py
loralib/adalora.py
loralib/layers.py
loralib/utils.py
sam_lora_lib-0.1.0.dist-info/LICENSE.md
sam_lora_lib-0.1.0.dist-info/METADATA
sam_lora_lib-0.1.0.dist-info/WHEEL
sam_lora_lib-0.1.0.dist-info/top_level.txt
sam_lora_lib-0.1.0.dist-info/RECORD
