Metadata-Version: 2.1
Name: sam_lora_lib
Version: 0.1.0
Summary: PyTorch implementation of low-rank adaptation (LoRA), a parameter-efficient approach to adapt a large pre-trained deep learning model which obtains performance on-par with full fine-tuning.
Home-page: https://github.com/microsoft/LoRA
Author: sam test
Author-email: duanzhihua@189.cn
Classifier: Programming Language :: Python :: 3
Classifier: License :: OSI Approved :: MIT License
Classifier: Operating System :: OS Independent
Requires-Python: >=3.6
License-File: LICENSE.md
